dnikit_torch/__init__.py
dnikit_torch/_torch_producer.py
dnikit_torch-2.0.0.dist-info/WHEEL
dnikit_torch-2.0.0.dist-info/METADATA
dnikit_torch-2.0.0.dist-info/RECORD
